azure/quantum/__init__.py
azure/quantum/_constants.py
azure/quantum/_workspace_connection_params.py
azure/quantum/storage.py
azure/quantum/version.py
azure/quantum/workspace.py
azure/quantum/_client/__init__.py
azure/quantum/_client/_client.py
azure/quantum/_client/_configuration.py
azure/quantum/_client/_model_base.py
azure/quantum/_client/_patch.py
azure/quantum/_client/_serialization.py
azure/quantum/_client/_version.py
azure/quantum/_client/py.typed
azure/quantum/_client/models/__init__.py
azure/quantum/_client/models/_enums.py
azure/quantum/_client/models/_models.py
azure/quantum/_client/models/_patch.py
azure/quantum/_client/operations/__init__.py
azure/quantum/_client/operations/_operations.py
azure/quantum/_client/operations/_patch.py
azure/quantum/argument_types/__init__.py
azure/quantum/argument_types/types.py
azure/quantum/cirq/__init__.py
azure/quantum/cirq/job.py
azure/quantum/cirq/service.py
azure/quantum/cirq/targets/__init__.py
azure/quantum/cirq/targets/ionq.py
azure/quantum/cirq/targets/quantinuum.py
azure/quantum/cirq/targets/target.py
azure/quantum/job/__init__.py
azure/quantum/job/base_job.py
azure/quantum/job/filtered_job.py
azure/quantum/job/job.py
azure/quantum/job/job_failed_with_results_error.py
azure/quantum/job/session.py
azure/quantum/job/workspace_item.py
azure/quantum/job/workspace_item_factory.py
azure/quantum/qiskit/__init__.py
azure/quantum/qiskit/job.py
azure/quantum/qiskit/provider.py
azure/quantum/qiskit/backends/__init__.py
azure/quantum/qiskit/backends/backend.py
azure/quantum/qiskit/backends/ionq.py
azure/quantum/qiskit/backends/qci.py
azure/quantum/qiskit/backends/quantinuum.py
azure/quantum/qiskit/backends/rigetti.py
azure/quantum/target/__init__.py
azure/quantum/target/ionq.py
azure/quantum/target/params.py
azure/quantum/target/quantinuum.py
azure/quantum/target/target.py
azure/quantum/target/target_factory.py
azure/quantum/target/pasqal/__init__.py
azure/quantum/target/pasqal/result.py
azure_quantum-3.4.0.dist-info/METADATA
azure_quantum-3.4.0.dist-info/WHEEL
azure_quantum-3.4.0.dist-info/top_level.txt
azure_quantum-3.4.0.dist-info/RECORD
