Metadata-Version: 2.1
Name: azure-quantum
Version: 3.4.0
Summary: Python client for Azure Quantum
Home-page: https://github.com/microsoft/azure-quantum-python
Author: Microsoft
License: MIT License
Classifier: Programming Language :: Python :: 3
Classifier: License :: OSI Approved :: MIT License
Classifier: Operating System :: OS Independent
Requires-Python: >=3.8
Requires-Dist: azure-core<2.0,>=1.30
Requires-Dist: azure-identity<2.0,>=1.17
Requires-Dist: azure-storage-blob==12.20
Requires-Dist: msrest<1.0,>=0.7.1
Requires-Dist: numpy>=1.21.0
Requires-Dist: deprecated<2.0,>=1.2.12
Requires-Dist: Markdown>=3.4.1
Requires-Dist: python-markdown-math>=0.8
Provides-Extra: all
Requires-Dist: cirq-core<=1.4.1,>=1.3.0; extra == "all"
Requires-Dist: cirq-ionq<=1.4.1,>=1.3.0; extra == "all"
Requires-Dist: pytest>=7.1.2; extra == "all"
Requires-Dist: pytest-xdist<4.0,>=3.8.0; extra == "all"
Requires-Dist: vcrpy>=4.3.1; extra == "all"
Requires-Dist: azure-devtools<2.0,>=1.2.0; extra == "all"
Requires-Dist: graphviz>=0.20.1; extra == "all"
Requires-Dist: pulser<0.19,>=0.18; extra == "all"
Requires-Dist: qiskit-ionq<0.6,>=0.5; extra == "all"
Requires-Dist: qsharp[qiskit]<2.0,>=1.9.0; extra == "all"
Requires-Dist: pyqir<0.11,>=0.10.6; extra == "all"
Requires-Dist: Markdown<4.0,>=3.4.1; extra == "all"
Requires-Dist: python-markdown-math<1.0,>=0.8.0; extra == "all"
Requires-Dist: qsharp<2.0,>=1.0.33; extra == "all"
Requires-Dist: pyquil==4.13.1; extra == "all"
Provides-Extra: cirq
Requires-Dist: cirq-core<=1.4.1,>=1.3.0; extra == "cirq"
Requires-Dist: cirq-ionq<=1.4.1,>=1.3.0; extra == "cirq"
Provides-Extra: dev
Requires-Dist: pytest>=7.1.2; extra == "dev"
Requires-Dist: pytest-xdist<4.0,>=3.8.0; extra == "dev"
Requires-Dist: vcrpy>=4.3.1; extra == "dev"
Requires-Dist: azure-devtools<2.0,>=1.2.0; extra == "dev"
Requires-Dist: graphviz>=0.20.1; extra == "dev"
Provides-Extra: pulser
Requires-Dist: pulser<0.19,>=0.18; extra == "pulser"
Provides-Extra: qiskit
Requires-Dist: qiskit-ionq<0.6,>=0.5; extra == "qiskit"
Requires-Dist: qsharp[qiskit]<2.0,>=1.9.0; extra == "qiskit"
Requires-Dist: pyqir<0.11,>=0.10.6; extra == "qiskit"
Requires-Dist: Markdown<4.0,>=3.4.1; extra == "qiskit"
Requires-Dist: python-markdown-math<1.0,>=0.8.0; extra == "qiskit"
Provides-Extra: qsharp
Requires-Dist: qsharp<2.0,>=1.0.33; extra == "qsharp"
Provides-Extra: quil
Requires-Dist: pyquil==4.13.1; extra == "quil"
